{ "graph": {
  "metadata": {
    "goal": "G0"
  },
  "nodes": {
    "G0": {
      "label": " \u22a2 I\u2081\n",
      "metadata": {
        "kind": "OR"
      }
    },
    "G1": {
      "label": " \u22a2 I\u2081\n",
      "metadata": {
        "kind": "OR"
      }
    },
    "G2": {
      "label": " \u22a2 I\u2081\n",
      "metadata": {
        "kind": "OR"
      }
    },
    "G4": {
      "label": " \u22a2 I\u2081\n",
      "metadata": {
        "kind": "OR"
      }
    },
    "G5": {
      "label": " \u22a2 True\n",
      "metadata": {
        "kind": "OR"
      }
    },
    "G3": {
      "label": " \u22a2 True\n",
      "metadata": {
        "kind": "OR"
      }
    },
    "R0": {
      "label": "[0/safe] safe|tactic|global|Aesop.BuiltinRule.preprocess",
      "metadata": {
        "kind": "AND"
      }
    },
    "R1": {
      "label": "[50.0000%] unsafe|constructors|global|I\u2081",
      "metadata": {
        "kind": "AND"
      }
    },
    "R3": {
      "label": "[50.0000%] unsafe|constructors|global|I\u2081",
      "metadata": {
        "kind": "AND"
      }
    },
    "R4": {
      "label": "[50.0000%] unsafe|constructors|global|I\u2081",
      "metadata": {
        "kind": "AND"
      }
    },
    "R2": {
      "label": "[50.0000%] unsafe|constructors|global|I\u2081",
      "metadata": {
        "kind": "AND"
      }
    },
    "R-1": {
      "label": " provenByNormalization",
      "metadata": {
        "kind": "AND"
      }
    }
  },
  "edges": [
    {
      "source": "G2",
      "target": "R4"
    },
    {
      "source": "G1",
      "target": "R1"
    },
    {
      "source": "G0",
      "target": "R0"
    },
    {
      "source": "G2",
      "target": "R3"
    },
    {
      "source": "R4",
      "target": "G5"
    },
    {
      "source": "G1",
      "target": "R2"
    },
    {
      "source": "R2",
      "target": "G3"
    },
    {
      "source": "R0",
      "target": "G1"
    },
    {
      "source": "G3",
      "target": "R-1"
    },
    {
      "source": "R3",
      "target": "G4"
    },
    {
      "source": "R1",
      "target": "G2"
    }
  ]
}
}