{ "graph": {
  "metadata": {
    "goal": "G0"
  },
  "nodes": {
    "G0": {
      "label": " case cons\n\u03b1 : Type u_1\nP : \u03b1 \u2192 Prop\nhead\u271d : \u03b1\ntail\u271d : List \u03b1\ntail_ih\u271d : All P tail\u271d \u2194 \u2200 (a : \u03b1), a \u2208 tail\u271d \u2192 P a\n\u22a2 All P (head\u271d :: tail\u271d) \u2194 \u2200 (a : \u03b1), a \u2208 head\u271d :: tail\u271d \u2192 P a\n",
      "metadata": {
        "kind": "OR"
      }
    },
    "G1": {
      "label": " \u03b1 : Type u_1\nP : \u03b1 \u2192 Prop\nhead : \u03b1\ntail : List \u03b1\ntail_ih : All P tail \u2194 \u2200 (a : \u03b1), a \u2208 tail \u2192 P a\n\u22a2 All P (head :: tail) \u2194 \u2200 (a : \u03b1), a \u2208 head :: tail \u2192 P a\n",
      "metadata": {
        "kind": "OR"
      }
    },
    "R0": {
      "label": "[0/safe] safe|tactic|global|Aesop.BuiltinRule.preprocess",
      "metadata": {
        "kind": "AND"
      }
    },
    "R-1": {
      "label": " provenByNormalization",
      "metadata": {
        "kind": "AND"
      }
    }
  },
  "edges": [
    {
      "source": "G0",
      "target": "R0"
    },
    {
      "source": "G1",
      "target": "R-1"
    },
    {
      "source": "R0",
      "target": "G1"
    }
  ]
}
}