{ "graph": {
  "metadata": {
    "goal": "G0"
  },
  "nodes": {
    "G0": {
      "label": " \u03b1 : Type\nP : \u03b1 \u2192 Prop\nx y z : \u03b1\nh\u2081 : x \u224d y\nh\u2082 : y \u224d z\nh\u2083 : P x\n\u22a2 P z\n",
      "metadata": {
        "kind": "OR"
      }
    },
    "G1": {
      "label": " \u03b1 : Type\nP : \u03b1 \u2192 Prop\nx y z : \u03b1\nh\u2081 : x \u224d y\nh\u2082 : y \u224d z\nh\u2083 : P x\n\u22a2 P z\n",
      "metadata": {
        "kind": "OR"
      }
    },
    "R0": {
      "label": "[0/safe] safe|tactic|global|Aesop.BuiltinRule.preprocess",
      "metadata": {
        "kind": "AND"
      }
    },
    "R1": {
      "label": "[-50/safe] safe|tactic|global|Aesop.BuiltinRules.assumption",
      "metadata": {
        "kind": "AND"
      }
    }
  },
  "edges": [
    {
      "source": "G0",
      "target": "R0"
    },
    {
      "source": "G1",
      "target": "R1"
    },
    {
      "source": "R0",
      "target": "G1"
    }
  ]
}
}