{ "graph": {
  "metadata": {
    "goal": "0"
  },
  "nodes": {
    "2": {
      "metadata": {
        "kind": "AND"
      }
    },
    "4": {
      "metadata": {
        "kind": "AND"
      }
    },
    "11": {
      "metadata": {
        "kind": "AND"
      }
    },
    "13": {
      "metadata": {
        "kind": "AND"
      }
    },
    "14": {
      "metadata": {
        "kind": "AND"
      }
    },
    "15": {
      "metadata": {
        "kind": "AND"
      }
    },
    "17": {
      "metadata": {
        "kind": "AND"
      }
    },
    "20": {
      "metadata": {
        "kind": "AND"
      }
    },
    "32": {
      "metadata": {
        "kind": "AND"
      }
    },
    "33": {
      "metadata": {
        "kind": "AND"
      }
    },
    "35": {
      "metadata": {
        "kind": "AND"
      }
    },
    "52": {
      "metadata": {
        "kind": "AND"
      }
    },
    "53": {
      "metadata": {
        "kind": "AND"
      }
    },
    "55": {
      "metadata": {
        "kind": "AND"
      }
    },
    "66": {
      "metadata": {
        "kind": "AND"
      }
    },
    "67": {
      "metadata": {
        "kind": "AND"
      }
    },
    "68": {
      "metadata": {
        "kind": "AND"
      }
    },
    "70": {
      "metadata": {
        "kind": "AND"
      }
    },
    "88": {
      "metadata": {
        "kind": "AND"
      }
    },
    "99": {
      "metadata": {
        "kind": "AND"
      }
    },
    "101": {
      "metadata": {
        "kind": "AND"
      }
    },
    "102": {
      "metadata": {
        "kind": "AND"
      }
    },
    "156": {
      "metadata": {
        "kind": "AND"
      }
    },
    "163": {
      "metadata": {
        "kind": "AND"
      }
    },
    "181": {
      "metadata": {
        "kind": "AND"
      }
    },
    "189": {
      "metadata": {
        "kind": "AND"
      }
    },
    "195": {
      "metadata": {
        "kind": "AND"
      }
    },
    "211": {
      "metadata": {
        "kind": "AND"
      }
    },
    "212": {
      "metadata": {
        "kind": "AND"
      }
    },
    "213": {
      "metadata": {
        "kind": "AND"
      }
    },
    "0": {
      "metadata": {
        "kind": "OR"
      }
    },
    "5": {
      "metadata": {
        "kind": "OR"
      }
    },
    "6": {
      "metadata": {
        "kind": "OR"
      }
    },
    "7": {
      "metadata": {
        "kind": "OR"
      }
    },
    "8": {
      "metadata": {
        "kind": "OR"
      }
    },
    "9": {
      "metadata": {
        "kind": "OR"
      }
    },
    "10": {
      "metadata": {
        "kind": "OR"
      }
    },
    "21": {
      "metadata": {
        "kind": "OR"
      }
    },
    "22": {
      "metadata": {
        "kind": "OR"
      }
    },
    "23": {
      "metadata": {
        "kind": "OR"
      }
    },
    "24": {
      "metadata": {
        "kind": "OR"
      }
    },
    "25": {
      "metadata": {
        "kind": "OR"
      }
    },
    "26": {
      "metadata": {
        "kind": "OR"
      }
    },
    "27": {
      "metadata": {
        "kind": "OR"
      }
    },
    "28": {
      "metadata": {
        "kind": "OR"
      }
    },
    "29": {
      "metadata": {
        "kind": "OR"
      }
    },
    "30": {
      "metadata": {
        "kind": "OR"
      }
    },
    "36": {
      "metadata": {
        "kind": "OR"
      }
    },
    "37": {
      "metadata": {
        "kind": "OR"
      }
    },
    "38": {
      "metadata": {
        "kind": "OR"
      }
    },
    "39": {
      "metadata": {
        "kind": "OR"
      }
    },
    "40": {
      "metadata": {
        "kind": "OR"
      }
    },
    "41": {
      "metadata": {
        "kind": "OR"
      }
    },
    "42": {
      "metadata": {
        "kind": "OR"
      }
    },
    "43": {
      "metadata": {
        "kind": "OR"
      }
    },
    "44": {
      "metadata": {
        "kind": "OR"
      }
    },
    "45": {
      "metadata": {
        "kind": "OR"
      }
    },
    "46": {
      "metadata": {
        "kind": "OR"
      }
    },
    "47": {
      "metadata": {
        "kind": "OR"
      }
    },
    "48": {
      "metadata": {
        "kind": "OR"
      }
    },
    "49": {
      "metadata": {
        "kind": "OR"
      }
    },
    "58": {
      "metadata": {
        "kind": "OR"
      }
    },
    "59": {
      "metadata": {
        "kind": "OR"
      }
    },
    "60": {
      "metadata": {
        "kind": "OR"
      }
    },
    "61": {
      "metadata": {
        "kind": "OR"
      }
    },
    "62": {
      "metadata": {
        "kind": "OR"
      }
    },
    "63": {
      "metadata": {
        "kind": "OR"
      }
    },
    "64": {
      "metadata": {
        "kind": "OR"
      }
    },
    "71": {
      "metadata": {
        "kind": "OR"
      }
    },
    "72": {
      "metadata": {
        "kind": "OR"
      }
    },
    "73": {
      "metadata": {
        "kind": "OR"
      }
    },
    "74": {
      "metadata": {
        "kind": "OR"
      }
    },
    "75": {
      "metadata": {
        "kind": "OR"
      }
    },
    "76": {
      "metadata": {
        "kind": "OR"
      }
    },
    "77": {
      "metadata": {
        "kind": "OR"
      }
    },
    "78": {
      "metadata": {
        "kind": "OR"
      }
    },
    "79": {
      "metadata": {
        "kind": "OR"
      }
    },
    "80": {
      "metadata": {
        "kind": "OR"
      }
    },
    "81": {
      "metadata": {
        "kind": "OR"
      }
    },
    "85": {
      "metadata": {
        "kind": "OR"
      }
    },
    "86": {
      "metadata": {
        "kind": "OR"
      }
    },
    "87": {
      "metadata": {
        "kind": "OR"
      }
    },
    "90": {
      "metadata": {
        "kind": "OR"
      }
    },
    "91": {
      "metadata": {
        "kind": "OR"
      }
    },
    "92": {
      "metadata": {
        "kind": "OR"
      }
    },
    "93": {
      "metadata": {
        "kind": "OR"
      }
    },
    "94": {
      "metadata": {
        "kind": "OR"
      }
    },
    "95": {
      "metadata": {
        "kind": "OR"
      }
    },
    "96": {
      "metadata": {
        "kind": "OR"
      }
    },
    "104": {
      "metadata": {
        "kind": "OR"
      }
    },
    "105": {
      "metadata": {
        "kind": "OR"
      }
    },
    "106": {
      "metadata": {
        "kind": "OR"
      }
    },
    "107": {
      "metadata": {
        "kind": "OR"
      }
    },
    "108": {
      "metadata": {
        "kind": "OR"
      }
    },
    "109": {
      "metadata": {
        "kind": "OR"
      }
    },
    "110": {
      "metadata": {
        "kind": "OR"
      }
    },
    "111": {
      "metadata": {
        "kind": "OR"
      }
    },
    "112": {
      "metadata": {
        "kind": "OR"
      }
    },
    "113": {
      "metadata": {
        "kind": "OR"
      }
    },
    "114": {
      "metadata": {
        "kind": "OR"
      }
    },
    "115": {
      "metadata": {
        "kind": "OR"
      }
    },
    "116": {
      "metadata": {
        "kind": "OR"
      }
    },
    "121": {
      "metadata": {
        "kind": "OR"
      }
    },
    "122": {
      "metadata": {
        "kind": "OR"
      }
    },
    "123": {
      "metadata": {
        "kind": "OR"
      }
    },
    "124": {
      "metadata": {
        "kind": "OR"
      }
    },
    "125": {
      "metadata": {
        "kind": "OR"
      }
    },
    "126": {
      "metadata": {
        "kind": "OR"
      }
    },
    "127": {
      "metadata": {
        "kind": "OR"
      }
    },
    "132": {
      "metadata": {
        "kind": "OR"
      }
    },
    "133": {
      "metadata": {
        "kind": "OR"
      }
    },
    "134": {
      "metadata": {
        "kind": "OR"
      }
    },
    "135": {
      "metadata": {
        "kind": "OR"
      }
    },
    "136": {
      "metadata": {
        "kind": "OR"
      }
    },
    "137": {
      "metadata": {
        "kind": "OR"
      }
    },
    "138": {
      "metadata": {
        "kind": "OR"
      }
    },
    "139": {
      "metadata": {
        "kind": "OR"
      }
    },
    "140": {
      "metadata": {
        "kind": "OR"
      }
    },
    "141": {
      "metadata": {
        "kind": "OR"
      }
    },
    "142": {
      "metadata": {
        "kind": "OR"
      }
    },
    "143": {
      "metadata": {
        "kind": "OR"
      }
    },
    "148": {
      "metadata": {
        "kind": "OR"
      }
    },
    "149": {
      "metadata": {
        "kind": "OR"
      }
    },
    "150": {
      "metadata": {
        "kind": "OR"
      }
    },
    "151": {
      "metadata": {
        "kind": "OR"
      }
    },
    "152": {
      "metadata": {
        "kind": "OR"
      }
    },
    "153": {
      "metadata": {
        "kind": "OR"
      }
    },
    "154": {
      "metadata": {
        "kind": "OR"
      }
    },
    "155": {
      "metadata": {
        "kind": "OR"
      }
    },
    "221": {
      "metadata": {
        "kind": "OR"
      }
    },
    "222": {
      "metadata": {
        "kind": "OR"
      }
    },
    "223": {
      "metadata": {
        "kind": "OR"
      }
    },
    "224": {
      "metadata": {
        "kind": "OR"
      }
    },
    "225": {
      "metadata": {
        "kind": "OR"
      }
    },
    "226": {
      "metadata": {
        "kind": "OR"
      }
    },
    "227": {
      "metadata": {
        "kind": "OR"
      }
    },
    "228": {
      "metadata": {
        "kind": "OR"
      }
    },
    "229": {
      "metadata": {
        "kind": "OR"
      }
    },
    "230": {
      "metadata": {
        "kind": "OR"
      }
    },
    "238": {
      "metadata": {
        "kind": "OR"
      }
    },
    "239": {
      "metadata": {
        "kind": "OR"
      }
    },
    "240": {
      "metadata": {
        "kind": "OR"
      }
    },
    "241": {
      "metadata": {
        "kind": "OR"
      }
    },
    "242": {
      "metadata": {
        "kind": "OR"
      }
    },
    "243": {
      "metadata": {
        "kind": "OR"
      }
    },
    "244": {
      "metadata": {
        "kind": "OR"
      }
    },
    "245": {
      "metadata": {
        "kind": "OR"
      }
    },
    "246": {
      "metadata": {
        "kind": "OR"
      }
    },
    "247": {
      "metadata": {
        "kind": "OR"
      }
    },
    "248": {
      "metadata": {
        "kind": "OR"
      }
    },
    "249": {
      "metadata": {
        "kind": "OR"
      }
    },
    "250": {
      "metadata": {
        "kind": "OR"
      }
    },
    "251": {
      "metadata": {
        "kind": "OR"
      }
    },
    "258": {
      "metadata": {
        "kind": "OR"
      }
    },
    "259": {
      "metadata": {
        "kind": "OR"
      }
    },
    "260": {
      "metadata": {
        "kind": "OR"
      }
    },
    "261": {
      "metadata": {
        "kind": "OR"
      }
    },
    "262": {
      "metadata": {
        "kind": "OR"
      }
    },
    "263": {
      "metadata": {
        "kind": "OR"
      }
    },
    "264": {
      "metadata": {
        "kind": "OR"
      }
    },
    "273": {
      "metadata": {
        "kind": "OR"
      }
    },
    "274": {
      "metadata": {
        "kind": "OR"
      }
    },
    "275": {
      "metadata": {
        "kind": "OR"
      }
    },
    "276": {
      "metadata": {
        "kind": "OR"
      }
    },
    "277": {
      "metadata": {
        "kind": "OR"
      }
    },
    "278": {
      "metadata": {
        "kind": "OR"
      }
    },
    "279": {
      "metadata": {
        "kind": "OR"
      }
    },
    "280": {
      "metadata": {
        "kind": "OR"
      }
    },
    "288": {
      "metadata": {
        "kind": "OR"
      }
    },
    "289": {
      "metadata": {
        "kind": "OR"
      }
    }
  },
  "edges": [
    {
      "source": "0",
      "target": "2"
    },
    {
      "source": "0",
      "target": "4"
    },
    {
      "source": "4",
      "target": "5"
    },
    {
      "source": "4",
      "target": "6"
    },
    {
      "source": "2",
      "target": "8"
    },
    {
      "source": "2",
      "target": "9"
    },
    {
      "source": "2",
      "target": "10"
    },
    {
      "source": "2",
      "target": "7"
    },
    {
      "source": "9",
      "target": "11"
    },
    {
      "source": "9",
      "target": "13"
    },
    {
      "source": "7",
      "target": "14"
    },
    {
      "source": "7",
      "target": "15"
    },
    {
      "source": "7",
      "target": "17"
    },
    {
      "source": "7",
      "target": "20"
    },
    {
      "source": "14",
      "target": "21"
    },
    {
      "source": "14",
      "target": "22"
    },
    {
      "source": "14",
      "target": "23"
    },
    {
      "source": "14",
      "target": "24"
    },
    {
      "source": "14",
      "target": "25"
    },
    {
      "source": "15",
      "target": "26"
    },
    {
      "source": "15",
      "target": "27"
    },
    {
      "source": "15",
      "target": "28"
    },
    {
      "source": "15",
      "target": "29"
    },
    {
      "source": "15",
      "target": "30"
    },
    {
      "source": "5",
      "target": "32"
    },
    {
      "source": "5",
      "target": "33"
    },
    {
      "source": "5",
      "target": "35"
    },
    {
      "source": "17",
      "target": "36"
    },
    {
      "source": "17",
      "target": "37"
    },
    {
      "source": "17",
      "target": "38"
    },
    {
      "source": "17",
      "target": "39"
    },
    {
      "source": "17",
      "target": "40"
    },
    {
      "source": "17",
      "target": "41"
    },
    {
      "source": "17",
      "target": "42"
    },
    {
      "source": "13",
      "target": "43"
    },
    {
      "source": "13",
      "target": "44"
    },
    {
      "source": "13",
      "target": "45"
    },
    {
      "source": "13",
      "target": "46"
    },
    {
      "source": "13",
      "target": "47"
    },
    {
      "source": "13",
      "target": "48"
    },
    {
      "source": "13",
      "target": "49"
    },
    {
      "source": "27",
      "target": "52"
    },
    {
      "source": "27",
      "target": "53"
    },
    {
      "source": "28",
      "target": "55"
    },
    {
      "source": "32",
      "target": "64"
    },
    {
      "source": "32",
      "target": "58"
    },
    {
      "source": "32",
      "target": "59"
    },
    {
      "source": "32",
      "target": "60"
    },
    {
      "source": "32",
      "target": "61"
    },
    {
      "source": "32",
      "target": "62"
    },
    {
      "source": "32",
      "target": "63"
    },
    {
      "source": "40",
      "target": "66"
    },
    {
      "source": "40",
      "target": "67"
    },
    {
      "source": "40",
      "target": "68"
    },
    {
      "source": "40",
      "target": "70"
    },
    {
      "source": "55",
      "target": "71"
    },
    {
      "source": "55",
      "target": "72"
    },
    {
      "source": "55",
      "target": "73"
    },
    {
      "source": "55",
      "target": "74"
    },
    {
      "source": "55",
      "target": "75"
    },
    {
      "source": "55",
      "target": "76"
    },
    {
      "source": "67",
      "target": "77"
    },
    {
      "source": "67",
      "target": "78"
    },
    {
      "source": "67",
      "target": "79"
    },
    {
      "source": "67",
      "target": "80"
    },
    {
      "source": "67",
      "target": "81"
    },
    {
      "source": "33",
      "target": "85"
    },
    {
      "source": "33",
      "target": "86"
    },
    {
      "source": "33",
      "target": "87"
    },
    {
      "source": "43",
      "target": "88"
    },
    {
      "source": "88",
      "target": "96"
    },
    {
      "source": "88",
      "target": "90"
    },
    {
      "source": "88",
      "target": "91"
    },
    {
      "source": "88",
      "target": "92"
    },
    {
      "source": "88",
      "target": "93"
    },
    {
      "source": "88",
      "target": "94"
    },
    {
      "source": "88",
      "target": "95"
    },
    {
      "source": "63",
      "target": "99"
    },
    {
      "source": "24",
      "target": "101"
    },
    {
      "source": "24",
      "target": "102"
    },
    {
      "source": "11",
      "target": "104"
    },
    {
      "source": "11",
      "target": "105"
    },
    {
      "source": "11",
      "target": "106"
    },
    {
      "source": "11",
      "target": "107"
    },
    {
      "source": "11",
      "target": "108"
    },
    {
      "source": "11",
      "target": "109"
    },
    {
      "source": "20",
      "target": "112"
    },
    {
      "source": "20",
      "target": "110"
    },
    {
      "source": "20",
      "target": "111"
    },
    {
      "source": "66",
      "target": "113"
    },
    {
      "source": "66",
      "target": "114"
    },
    {
      "source": "66",
      "target": "115"
    },
    {
      "source": "66",
      "target": "116"
    },
    {
      "source": "52",
      "target": "121"
    },
    {
      "source": "52",
      "target": "122"
    },
    {
      "source": "52",
      "target": "123"
    },
    {
      "source": "52",
      "target": "124"
    },
    {
      "source": "52",
      "target": "125"
    },
    {
      "source": "52",
      "target": "126"
    },
    {
      "source": "52",
      "target": "127"
    },
    {
      "source": "53",
      "target": "132"
    },
    {
      "source": "53",
      "target": "133"
    },
    {
      "source": "53",
      "target": "134"
    },
    {
      "source": "53",
      "target": "135"
    },
    {
      "source": "53",
      "target": "136"
    },
    {
      "source": "53",
      "target": "137"
    },
    {
      "source": "68",
      "target": "138"
    },
    {
      "source": "68",
      "target": "139"
    },
    {
      "source": "68",
      "target": "140"
    },
    {
      "source": "68",
      "target": "141"
    },
    {
      "source": "68",
      "target": "142"
    },
    {
      "source": "68",
      "target": "143"
    },
    {
      "source": "101",
      "target": "148"
    },
    {
      "source": "35",
      "target": "149"
    },
    {
      "source": "35",
      "target": "150"
    },
    {
      "source": "35",
      "target": "151"
    },
    {
      "source": "35",
      "target": "152"
    },
    {
      "source": "35",
      "target": "153"
    },
    {
      "source": "35",
      "target": "154"
    },
    {
      "source": "102",
      "target": "155"
    },
    {
      "source": "21",
      "target": "156"
    },
    {
      "source": "78",
      "target": "163"
    },
    {
      "source": "109",
      "target": "181"
    },
    {
      "source": "149",
      "target": "195"
    },
    {
      "source": "149",
      "target": "189"
    },
    {
      "source": "37",
      "target": "211"
    },
    {
      "source": "37",
      "target": "212"
    },
    {
      "source": "37",
      "target": "213"
    },
    {
      "source": "213",
      "target": "221"
    },
    {
      "source": "213",
      "target": "222"
    },
    {
      "source": "189",
      "target": "223"
    },
    {
      "source": "70",
      "target": "224"
    },
    {
      "source": "70",
      "target": "225"
    },
    {
      "source": "70",
      "target": "226"
    },
    {
      "source": "70",
      "target": "227"
    },
    {
      "source": "70",
      "target": "228"
    },
    {
      "source": "70",
      "target": "229"
    },
    {
      "source": "70",
      "target": "230"
    },
    {
      "source": "181",
      "target": "238"
    },
    {
      "source": "181",
      "target": "239"
    },
    {
      "source": "181",
      "target": "240"
    },
    {
      "source": "181",
      "target": "241"
    },
    {
      "source": "181",
      "target": "242"
    },
    {
      "source": "181",
      "target": "243"
    },
    {
      "source": "181",
      "target": "244"
    },
    {
      "source": "195",
      "target": "245"
    },
    {
      "source": "195",
      "target": "246"
    },
    {
      "source": "195",
      "target": "247"
    },
    {
      "source": "99",
      "target": "248"
    },
    {
      "source": "99",
      "target": "249"
    },
    {
      "source": "99",
      "target": "250"
    },
    {
      "source": "99",
      "target": "251"
    },
    {
      "source": "163",
      "target": "258"
    },
    {
      "source": "163",
      "target": "259"
    },
    {
      "source": "163",
      "target": "260"
    },
    {
      "source": "163",
      "target": "261"
    },
    {
      "source": "163",
      "target": "262"
    },
    {
      "source": "163",
      "target": "263"
    },
    {
      "source": "163",
      "target": "264"
    },
    {
      "source": "156",
      "target": "273"
    },
    {
      "source": "156",
      "target": "274"
    },
    {
      "source": "156",
      "target": "275"
    },
    {
      "source": "156",
      "target": "276"
    },
    {
      "source": "211",
      "target": "280"
    },
    {
      "source": "211",
      "target": "277"
    },
    {
      "source": "211",
      "target": "278"
    },
    {
      "source": "211",
      "target": "279"
    },
    {
      "source": "212",
      "target": "288"
    },
    {
      "source": "212",
      "target": "289"
    }
  ]
} }
